arlecchino/__init__.py
arlecchino/colors.txt
arlecchino/shades.txt
arlecchino-1.2.dist-info/METADATA
arlecchino-1.2.dist-info/WHEEL
arlecchino-1.2.dist-info/top_level.txt
arlecchino-1.2.dist-info/RECORD
